[
  {
    "День недели": "Понедельник",
    "Расписание": [
      {
        "Время": "10:10-11:40",
        "Неделя": "Обе недели",
        "Аудитория": {
          "Корпус": "У",
          "Номер аудитории": "УИК207"
        },
        "Группа": "20176",
        "Предмет": {
          "Наименование предмета": "Компьютерный анализ технологических объектов и процессов",
          "Тип занятия": "Лекция",
          "Дополнительная информация": ""
        },
        "Преподаватель": {
          "Фамилия": "Иванов",
          "Имя": "Сергей",
          "Отчество": "Юрьевич"
        }
      },
      {
        "Время": "11:50-13:20",
        "Неделя": "Обе недели",
        "Аудитория": {
          "Корпус": "У",
          "Номер аудитории": "УИК104"
        },
        "Группа": "20176",
        "Предмет": {
          "Наименование предмета": "Проектирование спецоборудования лазерной обработки",
          "Тип занятия": "Лабораторное занятие",
          "Дополнительная информация": ""
        },
        "Преподаватель": {
          "Фамилия": "Певзнер",
          "Имя": "Яков",
          "Отчество": "Борисович"
        }
      },
      {
        "Время": "14:00-15:30",
        "Неделя": "Обе недели",
        "Аудитория": {
          "Корпус": "У",
          "Номер аудитории": "УИК207"
        },
        "Группа": "20176",
        "Предмет": {
          "Наименование предмета": "Проектирование спецоборудования лазерной обработки",
          "Тип занятия": "Практическое занятие",
          "Дополнительная информация": ""
        },
        "Преподаватель": {
          "Фамилия": "Певзнер",
          "Имя": "Яков",
          "Отчество": "Борисович"
        }
      }
    ]
  },
  {
    "День недели": "Среда",
    "Расписание": [
      {
        "Время": "10:10-11:40",
        "Неделя": "Верхняя неделя",
        "Аудитория": {
          "Корпус": "У",
          "Номер аудитории": "УИК207"
        },
        "Группа": "20176",
        "Предмет": {
          "Наименование предмета": "Компьютерный анализ технологических объектов и процессов",
          "Тип занятия": "Практическое занятие",
          "Дополнительная информация": ""
        },
        "Преподаватель": {
          "Фамилия": "Юдин",
          "Имя": "Илья",
          "Отчество": "Николаевич"
        }
      },
      {
        "Время": "10:10-11:40",
        "Неделя": "Нижняя неделя",
        "Аудитория": {
          "Корпус": "У",
          "Номер аудитории": "УИК207"
        },
        "Группа": "20176",
        "Предмет": {
          "Наименование предмета": "Прикладные методы анализа материалов",
          "Тип занятия": "Лекция",
          "Дополнительная информация": ""
        },
        "Преподаватель": {
          "Фамилия": "Климова-Корсмик",
          "Имя": "Ольга",
          "Отчество": "Геннадьевна"
        }
      },
      {
        "Время": "11:50-13:20",
        "Неделя": "Верхняя неделя",
        "Аудитория": {
          "Корпус": "У",
          "Номер аудитории": "УИК207"
        },
        "Группа": "20176",
        "Предмет": {
          "Наименование предмета": "Компьютерный анализ технологических объектов и процессов",
          "Тип занятия": "Практическое занятие",
          "Дополнительная информация": ""
        },
        "Преподаватель": {
          "Фамилия": "Юдин",
          "Имя": "Илья",
          "Отчество": "Николаевич"
        }
      },
      {
        "Время": "11:50-13:20",
        "Неделя": "Нижняя неделя",
        "Аудитория": {
          "Корпус": "У",
          "Номер аудитории": "УИК208"
        },
        "Группа": "20176",
        "Предмет": {
          "Наименование предмета": "Прикладные методы анализа материалов",
          "Тип занятия": "Практическое занятие",
          "Дополнительная информация": ""
        },
        "Преподаватель": {
          "Фамилия": "Гущина",
          "Имя": "Марина",
          "Отчество": "Олеговна"
        }
      },
      {
        "Время": "14:00-15:30",
        "Неделя": "Верхняя неделя",
        "Аудитория": {
          "Корпус": "У",
          "Номер аудитории": "УИК104"
        },
        "Группа": "20176",
        "Предмет": {
          "Наименование предмета": "Технологии обработки материалов концентрированными потоками энергии",
          "Тип занятия": "Лабораторное занятие",
          "Дополнительная информация": ""
        },
        "Преподаватель": {
          "Фамилия": "Цибульский",
          "Имя": "Игорь",
          "Отчество": "Александрович"
        }
      },
      {
        "Время": "14:00-15:30",
        "Неделя": "Нижняя неделя",
        "Аудитория": {
          "Корпус": "У",
          "Номер аудитории": "УИК207"
        },
        "Группа": "20176",
        "Предмет": {
          "Наименование предмета": "Технологии обработки материалов концентрированными потоками энергии",
          "Тип занятия": "Лекция",
          "Дополнительная информация": ""
        },
        "Преподаватель": {
          "Фамилия": "Цибульский",
          "Имя": "Игорь",
          "Отчество": "Александрович"
        }
      },
      {
        "Время": "15:40-17:10",
        "Неделя": "Верхняя неделя",
        "Аудитория": {
          "Корпус": "У",
          "Номер аудитории": "УИК104"
        },
        "Группа": "20176",
        "Предмет": {
          "Наименование предмета": "Технологии обработки материалов концентрированными потоками энергии",
          "Тип занятия": "Лабораторное занятие",
          "Дополнительная информация": ""
        },
        "Преподаватель": {
          "Фамилия": "Цибульский",
          "Имя": "Игорь",
          "Отчество": "Александрович"
        }
      }
    ]
  },
  {
    "День недели": "Пятница",
    "Расписание": [
      {
        "Время": "14:00-15:30",
        "Неделя": "Верхняя неделя",
        "Аудитория": {
          "Корпус": "У",
          "Номер аудитории": "505"
        },
        "Группа": "20176",
        "Предмет": {
          "Наименование предмета": "Иностранный язык в профессиональной деятельности",
          "Тип занятия": "Практическое занятие",
          "Дополнительная информация": ""
        },
        "Преподаватель": {
          "Фамилия": "Трофимова",
          "Имя": "Светлана",
          "Отчество": "Леонидовна"
        }
      },
      {
        "Время": "14:00-15:30",
        "Неделя": "Нижняя неделя",
        "Аудитория": {
          "Корпус": "У",
          "Номер аудитории": "УИК207"
        },
        "Группа": "20176",
        "Предмет": {
          "Наименование предмета": "Аддитивные технологии",
          "Тип занятия": "Лекция",
          "Дополнительная информация": ""
        },
        "Преподаватель": {
          "Фамилия": "Земляков",
          "Имя": "Евгений",
          "Отчество": "Вячеславович"
        }
      },
      {
        "Время": "15:40-17:10",
        "Неделя": "Верхняя неделя",
        "Аудитория": {
          "Корпус": "У",
          "Номер аудитории": "407"
        },
        "Группа": "20176",
        "Предмет": {
          "Наименование предмета": "Философские проблемы науки и техники",
          "Тип занятия": "Практическое занятие",
          "Дополнительная информация": ""
        },
        "Преподаватель": {
          "Фамилия": "Медведев",
          "Имя": "Владимир",
          "Отчество": "Иванович"
        }
      },
      {
        "Время": "15:40-17:10",
        "Неделя": "Нижняя неделя",
        "Аудитория": {
          "Корпус": "У",
          "Номер аудитории": "УИК104"
        },
        "Группа": "20176",
        "Предмет": {
          "Наименование предмета": "Аддитивные технологии",
          "Тип занятия": "Лабораторное занятие",
          "Дополнительная информация": ""
        },
        "Преподаватель": {
          "Фамилия": "Вильданов",
          "Имя": "Артур",
          "Отчество": "Маратович"
        }
      },
      {
        "Время": "17:20-18:50",
        "Неделя": "Верхняя неделя",
        "Аудитория": {
          "Корпус": "У",
          "Номер аудитории": "504"
        },
        "Группа": "20176",
        "Предмет": {
          "Наименование предмета": "Философские проблемы науки и техники",
          "Тип занятия": "Лекция",
          "Дополнительная информация": ""
        },
        "Преподаватель": {
          "Фамилия": "Медведев",
          "Имя": "Владимир",
          "Отчество": "Иванович"
        }
      },
      {
        "Время": "17:20-18:50",
        "Неделя": "Нижняя неделя",
        "Аудитория": {
          "Корпус": "У",
          "Номер аудитории": "УИК104"
        },
        "Группа": "20176",
        "Предмет": {
          "Наименование предмета": "Аддитивные технологии",
          "Тип занятия": "Лабораторное занятие",
          "Дополнительная информация": ""
        },
        "Преподаватель": {
          "Фамилия": "Вильданов",
          "Имя": "Артур",
          "Отчество": "Маратович"
        }
      }
    ]
  }
]