[
  {
    "День недели": "Понедельник",
    "Расписание": [
      {
        "Время": "17:20-18:50",
        "Неделя": "Обе недели",
        "Аудитория": {
          "Корпус": "Б",
          "Номер аудитории": "ЛУИТ"
        },
        "Группа": "4260",
        "Предмет": {
          "Наименование предмета": "Развитие сетей распределения",
          "Тип занятия": "Лекция",
          "Дополнительная информация": "с 06.11 по 25.12"
        },
        "Преподаватель": {
          "Фамилия": "Смирнова",
          "Имя": "Ольга",
          "Отчество": "Александровна"
        }
      },
      {
        "Время": "19:00-20:30",
        "Неделя": "Обе недели",
        "Аудитория": {
          "Корпус": "Б",
          "Номер аудитории": "ЛУИТ"
        },
        "Группа": "4260",
        "Предмет": {
          "Наименование предмета": "Развитие сетей распределения",
          "Тип занятия": "Практическое занятие",
          "Дополнительная информация": "с 06.11 по 25.12"
        },
        "Преподаватель": {
          "Фамилия": "Смирнова",
          "Имя": "Ольга",
          "Отчество": "Александровна"
        }
      },
      {
        "Время": "19:00-20:30",
        "Неделя": "Обе недели",
        "Аудитория": {
          "Корпус": "М",
          "Номер аудитории": "32"
        },
        "Группа": "4260",
        "Предмет": {
          "Наименование предмета": "Экономика отраслевых рынков",
          "Тип занятия": "Лекция",
          "Дополнительная информация": "с 04.09.по 30.10"
        },
        "Преподаватель": {
          "Фамилия": "Красовская",
          "Имя": "Инна",
          "Отчество": "Петровна"
        }
      },
      {
        "Время": "20:40-22:10",
        "Неделя": "Обе недели",
        "Аудитория": {
          "Корпус": "М",
          "Номер аудитории": "32"
        },
        "Группа": "4260",
        "Предмет": {
          "Наименование предмета": "Экономика отраслевых рынков",
          "Тип занятия": "Практическое занятие",
          "Дополнительная информация": "с 04.09.по 30.10"
        },
        "Преподаватель": {
          "Фамилия": "Красовская",
          "Имя": "Инна",
          "Отчество": "Петровна"
        }
      },
      {
        "Время": "20:40-22:10",
        "Неделя": "Обе недели",
        "Аудитория": {
          "Корпус": "Б",
          "Номер аудитории": "ЛУИТ"
        },
        "Группа": "4260",
        "Предмет": {
          "Наименование предмета": "Развитие сетей распределения",
          "Тип занятия": "Практическое занятие",
          "Дополнительная информация": "с 06.11 по 25.12"
        },
        "Преподаватель": {
          "Фамилия": "Смирнова",
          "Имя": "Ольга",
          "Отчество": "Александровна"
        }
      }
    ]
  },
  {
    "День недели": "Вторник",
    "Расписание": [
      {
        "Время": "15:40-17:10",
        "Неделя": "Обе недели",
        "Аудитория": {
          "Корпус": "М",
          "Номер аудитории": "11"
        },
        "Группа": "4260",
        "Предмет": {
          "Наименование предмета": "Управление и оптимизация финансовых ресурсов в логистике",
          "Тип занятия": "Лекция",
          "Дополнительная информация": "с 05.09 по 31.10"
        },
        "Преподаватель": {
          "Фамилия": "Палкина",
          "Имя": "Елена",
          "Отчество": "Сергеевна"
        }
      },
      {
        "Время": "17:20-18:50",
        "Неделя": "Обе недели",
        "Аудитория": {
          "Корпус": "М",
          "Номер аудитории": "11"
        },
        "Группа": "4260",
        "Предмет": {
          "Наименование предмета": "Управление и оптимизация финансовых ресурсов в логистике",
          "Тип занятия": "Практическое занятие",
          "Дополнительная информация": "с 05.09 по 31.10"
        },
        "Преподаватель": {
          "Фамилия": "Палкина",
          "Имя": "Елена",
          "Отчество": "Сергеевна"
        }
      },
      {
        "Время": "19:00-20:30",
        "Неделя": "Обе недели",
        "Аудитория": {
          "Корпус": "М",
          "Номер аудитории": "31"
        },
        "Группа": "4260",
        "Предмет": {
          "Наименование предмета": "Таможенное дело",
          "Тип занятия": "Лекция",
          "Дополнительная информация": "с 05.09 по 31.10"
        },
        "Преподаватель": {
          "Фамилия": "Палкина",
          "Имя": "Елена",
          "Отчество": "Сергеевна"
        }
      },
      {
        "Время": "20:40-22:10",
        "Неделя": "Обе недели",
        "Аудитория": {
          "Корпус": "М",
          "Номер аудитории": "31"
        },
        "Группа": "4260",
        "Предмет": {
          "Наименование предмета": "Таможенное дело",
          "Тип занятия": "Практическое занятие",
          "Дополнительная информация": "с 05.09 по 31.10"
        },
        "Преподаватель": {
          "Фамилия": "Палкина",
          "Имя": "Елена",
          "Отчество": "Сергеевна"
        }
      }
    ]
  },
  {
    "День недели": "Среда",
    "Расписание": [
      {
        "Время": "15:40-17:10",
        "Неделя": "Обе недели",
        "Аудитория": {
          "Корпус": "М",
          "Номер аудитории": "33"
        },
        "Группа": "4260",
        "Предмет": {
          "Наименование предмета": "Управление цепями поставок",
          "Тип занятия": "Лекция",
          "Дополнительная информация": "с06.09 по 06.12"
        },
        "Преподаватель": {
          "Фамилия": "Малышев",
          "Имя": "Евгений",
          "Отчество": "Анатольевич"
        }
      },
      {
        "Время": "17:20-18:50",
        "Неделя": "Обе недели",
        "Аудитория": {
          "Корпус": "М",
          "Номер аудитории": "33"
        },
        "Группа": "4260",
        "Предмет": {
          "Наименование предмета": "Управление цепями поставок",
          "Тип занятия": "Практическое занятие",
          "Дополнительная информация": "с06.09 по 06.12"
        },
        "Преподаватель": {
          "Фамилия": "Малышев",
          "Имя": "Евгений",
          "Отчество": "Анатольевич"
        }
      },
      {
        "Время": "19:00-20:30",
        "Неделя": "Обе недели",
        "Аудитория": {
          "Корпус": "М",
          "Номер аудитории": "33"
        },
        "Группа": "4260",
        "Предмет": {
          "Наименование предмета": "Организация мультимодальных перевозок",
          "Тип занятия": "Практическое занятие",
          "Дополнительная информация": "с06.09 по 01.11"
        },
        "Преподаватель": {
          "Фамилия": "Малышев",
          "Имя": "Евгений",
          "Отчество": "Анатольевич"
        }
      },
      {
        "Время": "20:40-22:10",
        "Неделя": "Обе недели",
        "Аудитория": {
          "Корпус": "М",
          "Номер аудитории": "33"
        },
        "Группа": "4260",
        "Предмет": {
          "Наименование предмета": "Организация мультимодальных перевозок",
          "Тип занятия": "Практическое занятие",
          "Дополнительная информация": "с06.09 по 01.11"
        },
        "Преподаватель": {
          "Фамилия": "Малышев",
          "Имя": "Евгений",
          "Отчество": "Анатольевич"
        }
      }
    ]
  },
  {
    "День недели": "Четверг",
    "Расписание": [
      {
        "Время": "17:20-18:50",
        "Неделя": "Обе недели",
        "Аудитория": {
          "Корпус": "Б",
          "Номер аудитории": "500"
        },
        "Группа": "4260",
        "Предмет": {
          "Наименование предмета": "Бережливое производство в судостроении",
          "Тип занятия": "Лекция",
          "Дополнительная информация": "с 09.11 по 11.01"
        },
        "Преподаватель": {
          "Фамилия": "Кох",
          "Имя": "Лариса",
          "Отчество": "Вячеславовна"
        }
      },
      {
        "Время": "19:00-20:30",
        "Неделя": "Обе недели",
        "Аудитория": {
          "Корпус": "М",
          "Номер аудитории": "33"
        },
        "Группа": "4260",
        "Предмет": {
          "Наименование предмета": "Страхование в морской логистике",
          "Тип занятия": "Лекция",
          "Дополнительная информация": "с 07.09 по 02.11"
        },
        "Преподаватель": {
          "Фамилия": "Биденко",
          "Имя": "Сергей",
          "Отчество": "Иванович"
        }
      },
      {
        "Время": "19:00-20:30",
        "Неделя": "Обе недели",
        "Аудитория": {
          "Корпус": "Б",
          "Номер аудитории": "500"
        },
        "Группа": "4260",
        "Предмет": {
          "Наименование предмета": "Бережливое производство в судостроении",
          "Тип занятия": "Практическое занятие",
          "Дополнительная информация": "с 09.11 по 11.01"
        },
        "Преподаватель": {
          "Фамилия": "Кох",
          "Имя": "Лариса",
          "Отчество": "Вячеславовна"
        }
      },
      {
        "Время": "20:40-22:10",
        "Неделя": "Обе недели",
        "Аудитория": {
          "Корпус": "М",
          "Номер аудитории": "33"
        },
        "Группа": "4260",
        "Предмет": {
          "Наименование предмета": "Страхование в морской логистике",
          "Тип занятия": "Практическое занятие",
          "Дополнительная информация": "с 07.09 по 02.11"
        },
        "Преподаватель": {
          "Фамилия": "Биденко",
          "Имя": "Сергей",
          "Отчество": "Иванович"
        }
      }
    ]
  },
  {
    "День недели": "Пятница",
    "Расписание": [
      {
        "Время": "08:30-10:00",
        "Неделя": "Обе недели",
        "Аудитория": {
          "Корпус": "А",
          "Номер аудитории": "ВУЦ"
        },
        "Группа": "4260",
        "Предмет": {
          "Наименование предмета": "Военная подготовка (офицеры запаса)",
          "Тип занятия": "Лекция",
          "Дополнительная информация": ""
        },
        "Преподаватель": {
          "Фамилия": "",
          "Имя": "",
          "Отчество": ""
        }
      },
      {
        "Время": "10:10-11:40",
        "Неделя": "Обе недели",
        "Аудитория": {
          "Корпус": "А",
          "Номер аудитории": "ВУЦ"
        },
        "Группа": "4260",
        "Предмет": {
          "Наименование предмета": "Военная подготовка (офицеры запаса)",
          "Тип занятия": "Лекция",
          "Дополнительная информация": ""
        },
        "Преподаватель": {
          "Фамилия": "",
          "Имя": "",
          "Отчество": ""
        }
      },
      {
        "Время": "11:50-13:20",
        "Неделя": "Обе недели",
        "Аудитория": {
          "Корпус": "А",
          "Номер аудитории": "ВУЦ"
        },
        "Группа": "4260",
        "Предмет": {
          "Наименование предмета": "Военная подготовка (офицеры запаса)",
          "Тип занятия": "Практическое занятие",
          "Дополнительная информация": ""
        },
        "Преподаватель": {
          "Фамилия": "",
          "Имя": "",
          "Отчество": ""
        }
      },
      {
        "Время": "14:00-15:30",
        "Неделя": "Обе недели",
        "Аудитория": {
          "Корпус": "А",
          "Номер аудитории": "ВУЦ"
        },
        "Группа": "4260",
        "Предмет": {
          "Наименование предмета": "Военная подготовка (офицеры запаса)",
          "Тип занятия": "Практическое занятие",
          "Дополнительная информация": ""
        },
        "Преподаватель": {
          "Фамилия": "",
          "Имя": "",
          "Отчество": ""
        }
      }
    ]
  },
  {
    "День недели": "Суббота",
    "Расписание": [
      {
        "Время": "10:10-11:40",
        "Неделя": "Обе недели",
        "Аудитория": {
          "Корпус": "Б",
          "Номер аудитории": "ЛУИТ"
        },
        "Группа": "4260",
        "Предмет": {
          "Наименование предмета": "Управление логистическими рисками",
          "Тип занятия": "Практическое занятие",
          "Дополнительная информация": "с 02.09 по 28.10"
        },
        "Преподаватель": {
          "Фамилия": "Биденко",
          "Имя": "Сергей",
          "Отчество": "Иванович"
        }
      },
      {
        "Время": "11:50-13:20",
        "Неделя": "Обе недели",
        "Аудитория": {
          "Корпус": "Б",
          "Номер аудитории": "ЛУИТ"
        },
        "Группа": "4260",
        "Предмет": {
          "Наименование предмета": "Управление логистическими рисками",
          "Тип занятия": "Практическое занятие",
          "Дополнительная информация": "с 02.09 по 28.10"
        },
        "Преподаватель": {
          "Фамилия": "Биденко",
          "Имя": "Сергей",
          "Отчество": "Иванович"
        }
      }
    ]
  }
]