[
  {
    "День недели": "Понедельник",
    "Расписание": [
      {
        "Время": "19:00-20:30",
        "Неделя": "Верхняя неделя",
        "Аудитория": {
          "Корпус": "У",
          "Номер аудитории": "418"
        },
        "Группа": "5410",
        "Предмет": {
          "Наименование предмета": "Технико-экономическое обоснование проектов",
          "Тип занятия": "Практическое занятие",
          "Дополнительная информация": ""
        },
        "Преподаватель": {
          "Фамилия": "Фролова",
          "Имя": "Вероника",
          "Отчество": "Александровна"
        }
      },
      {
        "Время": "19:00-20:30",
        "Неделя": "Нижняя неделя",
        "Аудитория": {
          "Корпус": "Б",
          "Номер аудитории": "207"
        },
        "Группа": "5410",
        "Предмет": {
          "Наименование предмета": "Судовые системы",
          "Тип занятия": "Лекция",
          "Дополнительная информация": ""
        },
        "Преподаватель": {
          "Фамилия": "Долгов",
          "Имя": "Дмитрий",
          "Отчество": "Сергеевич"
        }
      },
      {
        "Время": "20:40-22:10",
        "Неделя": "Верхняя неделя",
        "Аудитория": {
          "Корпус": "У",
          "Номер аудитории": "418"
        },
        "Группа": "5410",
        "Предмет": {
          "Наименование предмета": "Технико-экономическое обоснование проектов",
          "Тип занятия": "Практическое занятие",
          "Дополнительная информация": ""
        },
        "Преподаватель": {
          "Фамилия": "Фролова",
          "Имя": "Вероника",
          "Отчество": "Александровна"
        }
      },
      {
        "Время": "20:40-22:10",
        "Неделя": "Нижняя неделя",
        "Аудитория": {
          "Корпус": "Б",
          "Номер аудитории": "207"
        },
        "Группа": "5410",
        "Предмет": {
          "Наименование предмета": "Судовые системы",
          "Тип занятия": "Практическое занятие",
          "Дополнительная информация": ""
        },
        "Преподаватель": {
          "Фамилия": "Долгов",
          "Имя": "Дмитрий",
          "Отчество": "Сергеевич"
        }
      }
    ]
  },
  {
    "День недели": "Вторник",
    "Расписание": [
      {
        "Время": "19:00-20:30",
        "Неделя": "Верхняя неделя",
        "Аудитория": {
          "Корпус": "Б",
          "Номер аудитории": "609"
        },
        "Группа": "5410",
        "Предмет": {
          "Наименование предмета": "Основы систем автоматизированного проектирования",
          "Тип занятия": "Лекция",
          "Дополнительная информация": ""
        },
        "Преподаватель": {
          "Фамилия": "Кутенев",
          "Имя": "Андрей",
          "Отчество": "Александрович"
        }
      },
      {
        "Время": "19:00-20:30",
        "Неделя": "Нижняя неделя",
        "Аудитория": {
          "Корпус": "Б",
          "Номер аудитории": "610"
        },
        "Группа": "5410",
        "Предмет": {
          "Наименование предмета": "Основы проектирования судов",
          "Тип занятия": "Лекция",
          "Дополнительная информация": ""
        },
        "Преподаватель": {
          "Фамилия": "Власьев",
          "Имя": "Максим",
          "Отчество": "Валерьевич"
        }
      },
      {
        "Время": "20:40-22:10",
        "Неделя": "Верхняя неделя",
        "Аудитория": {
          "Корпус": "Б",
          "Номер аудитории": "609"
        },
        "Группа": "5410",
        "Предмет": {
          "Наименование предмета": "Основы систем автоматизированного проектирования",
          "Тип занятия": "Практическое занятие",
          "Дополнительная информация": ""
        },
        "Преподаватель": {
          "Фамилия": "Кутенев",
          "Имя": "Андрей",
          "Отчество": "Александрович"
        }
      }
    ]
  },
  {
    "День недели": "Среда",
    "Расписание": [
      {
        "Время": "19:00-20:30",
        "Неделя": "Нижняя неделя",
        "Аудитория": {
          "Корпус": "Б",
          "Номер аудитории": "422"
        },
        "Группа": "5410",
        "Предмет": {
          "Наименование предмета": "Теория корабля",
          "Тип занятия": "Лекция",
          "Дополнительная информация": ""
        },
        "Преподаватель": {
          "Фамилия": "Четвертаков",
          "Имя": "Алексей",
          "Отчество": "Михайлович"
        }
      },
      {
        "Время": "20:40-22:10",
        "Неделя": "Нижняя неделя",
        "Аудитория": {
          "Корпус": "Б",
          "Номер аудитории": "422"
        },
        "Группа": "5410",
        "Предмет": {
          "Наименование предмета": "Теория корабля",
          "Тип занятия": "Лабораторное занятие",
          "Дополнительная информация": ""
        },
        "Преподаватель": {
          "Фамилия": "Четвертаков",
          "Имя": "Алексей",
          "Отчество": "Михайлович"
        }
      }
    ]
  },
  {
    "День недели": "Четверг",
    "Расписание": [
      {
        "Время": "19:00-20:30",
        "Неделя": "Обе недели",
        "Аудитория": {
          "Корпус": "Б",
          "Номер аудитории": "521"
        },
        "Группа": "5410",
        "Предмет": {
          "Наименование предмета": "Сварка судовых конструкций",
          "Тип занятия": "Лекция",
          "Дополнительная информация": ""
        },
        "Преподаватель": {
          "Фамилия": "Муктепавел",
          "Имя": "Вольдемар",
          "Отчество": "Освальдович"
        }
      },
      {
        "Время": "20:40-22:10",
        "Неделя": "Верхняя неделя",
        "Аудитория": {
          "Корпус": "Б",
          "Номер аудитории": "521"
        },
        "Группа": "5410",
        "Предмет": {
          "Наименование предмета": "Сварка судовых конструкций",
          "Тип занятия": "Практическое занятие",
          "Дополнительная информация": ""
        },
        "Преподаватель": {
          "Фамилия": "Муктепавел",
          "Имя": "Вольдемар",
          "Отчество": "Освальдович"
        }
      },
      {
        "Время": "20:40-22:10",
        "Неделя": "Нижняя неделя",
        "Аудитория": {
          "Корпус": "Б",
          "Номер аудитории": "521"
        },
        "Группа": "5410",
        "Предмет": {
          "Наименование предмета": "Сварка судовых конструкций",
          "Тип занятия": "Лабораторное занятие",
          "Дополнительная информация": ""
        },
        "Преподаватель": {
          "Фамилия": "Муктепавел",
          "Имя": "Вольдемар",
          "Отчество": "Освальдович"
        }
      }
    ]
  },
  {
    "День недели": "Пятница",
    "Расписание": [
      {
        "Время": "19:00-20:30",
        "Неделя": "Обе недели",
        "Аудитория": {
          "Корпус": "Б",
          "Номер аудитории": "207"
        },
        "Группа": "5410",
        "Предмет": {
          "Наименование предмета": "Конструкция корпуса судов",
          "Тип занятия": "Лекция",
          "Дополнительная информация": ""
        },
        "Преподаватель": {
          "Фамилия": "Чижевский",
          "Имя": "Виталий",
          "Отчество": "Владимирович"
        }
      },
      {
        "Время": "20:40-22:10",
        "Неделя": "Обе недели",
        "Аудитория": {
          "Корпус": "Б",
          "Номер аудитории": "207"
        },
        "Группа": "5410",
        "Предмет": {
          "Наименование предмета": "Конструкция корпуса судов",
          "Тип занятия": "Практическое занятие",
          "Дополнительная информация": ""
        },
        "Преподаватель": {
          "Фамилия": "Чижевский",
          "Имя": "Виталий",
          "Отчество": "Владимирович"
        }
      }
    ]
  }
]