[
  {
    "День недели": "Понедельник",
    "Расписание": [
      {
        "Время": "08:30-10:00",
        "Неделя": "Нижняя неделя",
        "Аудитория": {
          "Корпус": "У",
          "Номер аудитории": "507"
        },
        "Группа": "1377",
        "Предмет": {
          "Наименование предмета": "Компьютерное проектирование объектов дизайна и декоративно-прикладного искусства",
          "Тип занятия": "Лекция",
          "Дополнительная информация": "Курскиева О.О."
        },
        "Преподаватель": {
          "Фамилия": "",
          "Имя": "",
          "Отчество": ""
        }
      },
      {
        "Время": "10:10-11:40",
        "Неделя": "Верхняя неделя",
        "Аудитория": {
          "Корпус": "У",
          "Номер аудитории": "245"
        },
        "Группа": "1377",
        "Предмет": {
          "Наименование предмета": "Методы исследования материалов",
          "Тип занятия": "Лекция",
          "Дополнительная информация": ""
        },
        "Преподаватель": {
          "Фамилия": "Фирсов",
          "Имя": "Анатолий",
          "Отчество": "Михайлович"
        }
      },
      {
        "Время": "10:10-11:40",
        "Неделя": "Нижняя неделя",
        "Аудитория": {
          "Корпус": "У",
          "Номер аудитории": "507"
        },
        "Группа": "1377",
        "Предмет": {
          "Наименование предмета": "Компьютерное проектирование объектов дизайна и декоративно-прикладного искусства",
          "Тип занятия": "Лабораторное занятие",
          "Дополнительная информация": "Курскиева О.О."
        },
        "Преподаватель": {
          "Фамилия": "",
          "Имя": "",
          "Отчество": ""
        }
      },
      {
        "Время": "11:50-13:20",
        "Неделя": "Верхняя неделя",
        "Аудитория": {
          "Корпус": "У",
          "Номер аудитории": "245"
        },
        "Группа": "1377",
        "Предмет": {
          "Наименование предмета": "Методы исследования материалов",
          "Тип занятия": "Практическое занятие",
          "Дополнительная информация": ""
        },
        "Преподаватель": {
          "Фамилия": "Фирсов",
          "Имя": "Анатолий",
          "Отчество": "Михайлович"
        }
      },
      {
        "Время": "11:50-13:20",
        "Неделя": "Нижняя неделя",
        "Аудитория": {
          "Корпус": "У",
          "Номер аудитории": "507"
        },
        "Группа": "1377",
        "Предмет": {
          "Наименование предмета": "Компьютерное проектирование объектов дизайна и декоративно-прикладного искусства",
          "Тип занятия": "Лабораторное занятие",
          "Дополнительная информация": "Курскиева О.О."
        },
        "Преподаватель": {
          "Фамилия": "",
          "Имя": "",
          "Отчество": ""
        }
      },
      {
        "Время": "14:00-15:30",
        "Неделя": "Верхняя неделя",
        "Аудитория": {
          "Корпус": "У",
          "Номер аудитории": "225"
        },
        "Группа": "1377",
        "Предмет": {
          "Наименование предмета": "Дизайн",
          "Тип занятия": "Лекция",
          "Дополнительная информация": ""
        },
        "Преподаватель": {
          "Фамилия": "Вьюношева",
          "Имя": "Юлия",
          "Отчество": "Викторовна"
        }
      },
      {
        "Время": "15:40-17:10",
        "Неделя": "Верхняя неделя",
        "Аудитория": {
          "Корпус": "У",
          "Номер аудитории": "225"
        },
        "Группа": "1377",
        "Предмет": {
          "Наименование предмета": "Дизайн",
          "Тип занятия": "Лабораторное занятие",
          "Дополнительная информация": ""
        },
        "Преподаватель": {
          "Фамилия": "Вьюношева",
          "Имя": "Юлия",
          "Отчество": "Викторовна"
        }
      }
    ]
  },
  {
    "День недели": "Вторник",
    "Расписание": [
      {
        "Время": "08:30-10:00",
        "Неделя": "Обе недели",
        "Аудитория": {
          "Корпус": "А",
          "Номер аудитории": "ВУЦ"
        },
        "Группа": "1377",
        "Предмет": {
          "Наименование предмета": "Военная подготовка (матросы/солдаты запаса)",
          "Тип занятия": "Лекция",
          "Дополнительная информация": ""
        },
        "Преподаватель": {
          "Фамилия": "",
          "Имя": "",
          "Отчество": ""
        }
      },
      {
        "Время": "08:30-10:00",
        "Неделя": "Обе недели",
        "Аудитория": {
          "Корпус": "А",
          "Номер аудитории": "ВУЦ"
        },
        "Группа": "1377",
        "Предмет": {
          "Наименование предмета": "Военная подготовка (офицеры запаса)",
          "Тип занятия": "Лекция",
          "Дополнительная информация": ""
        },
        "Преподаватель": {
          "Фамилия": "",
          "Имя": "",
          "Отчество": ""
        }
      }
    ]
  },
  {
    "День недели": "Среда",
    "Расписание": [
      {
        "Время": "10:10-11:40",
        "Неделя": "Верхняя неделя",
        "Аудитория": {
          "Корпус": "У",
          "Номер аудитории": "225"
        },
        "Группа": "1377",
        "Предмет": {
          "Наименование предмета": "Теория систем и системный анализ",
          "Тип занятия": "Лекция",
          "Дополнительная информация": ""
        },
        "Преподаватель": {
          "Фамилия": "Мунтиев",
          "Имя": "Павел",
          "Отчество": "Алексеевич"
        }
      },
      {
        "Время": "11:50-13:20",
        "Неделя": "Верхняя неделя",
        "Аудитория": {
          "Корпус": "У",
          "Номер аудитории": "225"
        },
        "Группа": "1377",
        "Предмет": {
          "Наименование предмета": "Теория систем и системный анализ",
          "Тип занятия": "Лекция",
          "Дополнительная информация": ""
        },
        "Преподаватель": {
          "Фамилия": "Мунтиев",
          "Имя": "Павел",
          "Отчество": "Алексеевич"
        }
      },
      {
        "Время": "11:50-13:20",
        "Неделя": "Нижняя неделя",
        "Аудитория": {
          "Корпус": "У",
          "Номер аудитории": ""
        },
        "Группа": "1377",
        "Предмет": {
          "Наименование предмета": "История керамики и фарфора",
          "Тип занятия": "Лекция",
          "Дополнительная информация": ""
        },
        "Преподаватель": {
          "Фамилия": "Мазитова",
          "Имя": "Гузаль",
          "Отчество": "Рафшановна"
        }
      },
      {
        "Время": "14:00-15:30",
        "Неделя": "Верхняя неделя",
        "Аудитория": {
          "Корпус": "У",
          "Номер аудитории": "225"
        },
        "Группа": "1377",
        "Предмет": {
          "Наименование предмета": "Теория систем и системный анализ",
          "Тип занятия": "Практическое занятие",
          "Дополнительная информация": ""
        },
        "Преподаватель": {
          "Фамилия": "Мунтиев",
          "Имя": "Павел",
          "Отчество": "Алексеевич"
        }
      },
      {
        "Время": "14:00-15:30",
        "Неделя": "Нижняя неделя",
        "Аудитория": {
          "Корпус": "У",
          "Номер аудитории": ""
        },
        "Группа": "1377",
        "Предмет": {
          "Наименование предмета": "История керамики и фарфора",
          "Тип занятия": "Лабораторное занятие",
          "Дополнительная информация": ""
        },
        "Преподаватель": {
          "Фамилия": "Мазитова",
          "Имя": "Гузаль",
          "Отчество": "Рафшановна"
        }
      },
      {
        "Время": "15:40-17:10",
        "Неделя": "Верхняя неделя",
        "Аудитория": {
          "Корпус": "У",
          "Номер аудитории": "245"
        },
        "Группа": "1377",
        "Предмет": {
          "Наименование предмета": "Обработка резанием",
          "Тип занятия": "Лекция",
          "Дополнительная информация": ""
        },
        "Преподаватель": {
          "Фамилия": "Греков",
          "Имя": "Андрей",
          "Отчество": "Анатольевич"
        }
      },
      {
        "Время": "15:40-17:10",
        "Неделя": "Нижняя неделя",
        "Аудитория": {
          "Корпус": "У",
          "Номер аудитории": ""
        },
        "Группа": "1377",
        "Предмет": {
          "Наименование предмета": "История керамики и фарфора",
          "Тип занятия": "Лабораторное занятие",
          "Дополнительная информация": ""
        },
        "Преподаватель": {
          "Фамилия": "Мазитова",
          "Имя": "Гузаль",
          "Отчество": "Рафшановна"
        }
      }
    ]
  },
  {
    "День недели": "Четверг",
    "Расписание": [
      {
        "Время": "10:10-11:40",
        "Неделя": "Обе недели",
        "Аудитория": {
          "Корпус": "У",
          "Номер аудитории": ""
        },
        "Группа": "1377",
        "Предмет": {
          "Наименование предмета": "Технология художественного литья",
          "Тип занятия": "Лекция",
          "Дополнительная информация": ""
        },
        "Преподаватель": {
          "Фамилия": "Петрова",
          "Имя": "Светлана",
          "Отчество": "Георгиевна"
        }
      },
      {
        "Время": "10:10-11:40",
        "Неделя": "Обе недели",
        "Аудитория": {
          "Корпус": "У",
          "Номер аудитории": "197"
        },
        "Группа": "1377",
        "Предмет": {
          "Наименование предмета": "Технология художественного литья",
          "Тип занятия": "Лекция",
          "Дополнительная информация": ""
        },
        "Преподаватель": {
          "Фамилия": "Петрова",
          "Имя": "Светлана",
          "Отчество": "Георгиевна"
        }
      },
      {
        "Время": "11:50-13:20",
        "Неделя": "Обе недели",
        "Аудитория": {
          "Корпус": "У",
          "Номер аудитории": ""
        },
        "Группа": "1377",
        "Предмет": {
          "Наименование предмета": "Технология художественного литья",
          "Тип занятия": "Лабораторное занятие",
          "Дополнительная информация": ""
        },
        "Преподаватель": {
          "Фамилия": "Петрова",
          "Имя": "Светлана",
          "Отчество": "Георгиевна"
        }
      },
      {
        "Время": "11:50-13:20",
        "Неделя": "Обе недели",
        "Аудитория": {
          "Корпус": "У",
          "Номер аудитории": "197"
        },
        "Группа": "1377",
        "Предмет": {
          "Наименование предмета": "Технология художественного литья",
          "Тип занятия": "Лабораторное занятие",
          "Дополнительная информация": ""
        },
        "Преподаватель": {
          "Фамилия": "Петрова",
          "Имя": "Светлана",
          "Отчество": "Георгиевна"
        }
      },
      {
        "Время": "14:00-15:30",
        "Неделя": "Верхняя неделя",
        "Аудитория": {
          "Корпус": "Конгресс-Центр",
          "Номер аудитории": "403"
        },
        "Группа": "1377",
        "Предмет": {
          "Наименование предмета": "Деловые коммуникации",
          "Тип занятия": "Лекция",
          "Дополнительная информация": ""
        },
        "Преподаватель": {
          "Фамилия": "Бабаева",
          "Имя": "Наталья",
          "Отчество": "Михайловна"
        }
      },
      {
        "Время": "14:00-15:30",
        "Неделя": "Нижняя неделя",
        "Аудитория": {
          "Корпус": "У",
          "Номер аудитории": "314"
        },
        "Группа": "1377",
        "Предмет": {
          "Наименование предмета": "Деловые коммуникации",
          "Тип занятия": "Практическое занятие",
          "Дополнительная информация": ""
        },
        "Преподаватель": {
          "Фамилия": "Бабаева",
          "Имя": "Наталья",
          "Отчество": "Михайловна"
        }
      },
      {
        "Время": "15:40-17:10",
        "Неделя": "Нижняя неделя",
        "Аудитория": {
          "Корпус": "У",
          "Номер аудитории": "245"
        },
        "Группа": "1377",
        "Предмет": {
          "Наименование предмета": "Обработка резанием",
          "Тип занятия": "Практическое занятие",
          "Дополнительная информация": ""
        },
        "Преподаватель": {
          "Фамилия": "Греков",
          "Имя": "Андрей",
          "Отчество": "Анатольевич"
        }
      }
    ]
  },
  {
    "День недели": "Пятница",
    "Расписание": [
      {
        "Время": "11:50-13:20",
        "Неделя": "Верхняя неделя",
        "Аудитория": {
          "Корпус": "У",
          "Номер аудитории": "191"
        },
        "Группа": "1377",
        "Предмет": {
          "Наименование предмета": "Художественное материаловедение",
          "Тип занятия": "Практическое занятие",
          "Дополнительная информация": ""
        },
        "Преподаватель": {
          "Фамилия": "Бабынькина",
          "Имя": "Анна",
          "Отчество": "Николаевна"
        }
      },
      {
        "Время": "11:50-13:20",
        "Неделя": "Нижняя неделя",
        "Аудитория": {
          "Корпус": "У",
          "Номер аудитории": "245а"
        },
        "Группа": "1377",
        "Предмет": {
          "Наименование предмета": "Художественное материаловедение",
          "Тип занятия": "Лекция",
          "Дополнительная информация": ""
        },
        "Преподаватель": {
          "Фамилия": "Бабынькина",
          "Имя": "Анна",
          "Отчество": "Николаевна"
        }
      },
      {
        "Время": "14:00-15:30",
        "Неделя": "Верхняя неделя",
        "Аудитория": {
          "Корпус": "У",
          "Номер аудитории": "245а"
        },
        "Группа": "1377",
        "Предмет": {
          "Наименование предмета": "Художественное материаловедение",
          "Тип занятия": "Лекция",
          "Дополнительная информация": ""
        },
        "Преподаватель": {
          "Фамилия": "Бабынькина",
          "Имя": "Анна",
          "Отчество": "Николаевна"
        }
      },
      {
        "Время": "14:00-15:30",
        "Неделя": "Нижняя неделя",
        "Аудитория": {
          "Корпус": "У",
          "Номер аудитории": "228"
        },
        "Группа": "1377",
        "Предмет": {
          "Наименование предмета": "Дизайн",
          "Тип занятия": "Лабораторное занятие",
          "Дополнительная информация": ""
        },
        "Преподаватель": {
          "Фамилия": "Вьюношева",
          "Имя": "Юлия",
          "Отчество": "Викторовна"
        }
      },
      {
        "Время": "15:40-17:10",
        "Неделя": "Верхняя неделя",
        "Аудитория": {
          "Корпус": "У",
          "Номер аудитории": "197"
        },
        "Группа": "1377",
        "Предмет": {
          "Наименование предмета": "Специальные технологии художественной обработки материалов",
          "Тип занятия": "Лекция",
          "Дополнительная информация": ""
        },
        "Преподаватель": {
          "Фамилия": "Емельянов",
          "Имя": "Александр",
          "Отчество": "Юрьевич"
        }
      },
      {
        "Время": "15:40-17:10",
        "Неделя": "Нижняя неделя",
        "Аудитория": {
          "Корпус": "У",
          "Номер аудитории": "108"
        },
        "Группа": "1377",
        "Предмет": {
          "Наименование предмета": "Специальные технологии художественной обработки материалов",
          "Тип занятия": "Лабораторное занятие",
          "Дополнительная информация": ""
        },
        "Преподаватель": {
          "Фамилия": "Емельянов",
          "Имя": "Александр",
          "Отчество": "Юрьевич"
        }
      },
      {
        "Время": "17:20-18:50",
        "Неделя": "Нижняя неделя",
        "Аудитория": {
          "Корпус": "У",
          "Номер аудитории": "108"
        },
        "Группа": "1377",
        "Предмет": {
          "Наименование предмета": "Специальные технологии художественной обработки материалов",
          "Тип занятия": "Лабораторное занятие",
          "Дополнительная информация": ""
        },
        "Преподаватель": {
          "Фамилия": "Емельянов",
          "Имя": "Александр",
          "Отчество": "Юрьевич"
        }
      }
    ]
  }
]