[
  {
    "День недели": "Понедельник",
    "Расписание": [
      {
        "Время": "19:00-20:30",
        "Неделя": "Верхняя неделя",
        "Аудитория": {
          "Корпус": "Б",
          "Номер аудитории": "610"
        },
        "Группа": "5216",
        "Предмет": {
          "Наименование предмета": "Проектирование подводных лодок",
          "Тип занятия": "Лекция",
          "Дополнительная информация": ""
        },
        "Преподаватель": {
          "Фамилия": "Калиничев",
          "Имя": "Алексей",
          "Отчество": "Евгеньевич"
        }
      },
      {
        "Время": "19:00-20:30",
        "Неделя": "Нижняя неделя",
        "Аудитория": {
          "Корпус": "Б",
          "Номер аудитории": "610"
        },
        "Группа": "5216",
        "Предмет": {
          "Наименование предмета": "Проектирование подводных лодок",
          "Тип занятия": "Практическое занятие",
          "Дополнительная информация": ""
        },
        "Преподаватель": {
          "Фамилия": "Калиничев",
          "Имя": "Алексей",
          "Отчество": "Евгеньевич"
        }
      },
      {
        "Время": "20:40-22:10",
        "Неделя": "Нижняя неделя",
        "Аудитория": {
          "Корпус": "Б",
          "Номер аудитории": "610"
        },
        "Группа": "5216",
        "Предмет": {
          "Наименование предмета": "Проектирование подводных лодок",
          "Тип занятия": "Практическое занятие",
          "Дополнительная информация": ""
        },
        "Преподаватель": {
          "Фамилия": "Калиничев",
          "Имя": "Алексей",
          "Отчество": "Евгеньевич"
        }
      }
    ]
  },
  {
    "День недели": "Вторник",
    "Расписание": [
      {
        "Время": "19:00-20:30",
        "Неделя": "Верхняя неделя",
        "Аудитория": {
          "Корпус": "Б",
          "Номер аудитории": "610"
        },
        "Группа": "5216",
        "Предмет": {
          "Наименование предмета": "Безопасность мореплавания",
          "Тип занятия": "Лекция",
          "Дополнительная информация": ""
        },
        "Преподаватель": {
          "Фамилия": "Власьев",
          "Имя": "Максим",
          "Отчество": "Валерьевич"
        }
      },
      {
        "Время": "20:40-22:10",
        "Неделя": "Верхняя неделя",
        "Аудитория": {
          "Корпус": "Б",
          "Номер аудитории": "610"
        },
        "Группа": "5216",
        "Предмет": {
          "Наименование предмета": "Безопасность мореплавания",
          "Тип занятия": "Лекция",
          "Дополнительная информация": ""
        },
        "Преподаватель": {
          "Фамилия": "Власьев",
          "Имя": "Максим",
          "Отчество": "Валерьевич"
        }
      }
    ]
  },
  {
    "День недели": "Среда",
    "Расписание": [
      {
        "Время": "19:00-20:30",
        "Неделя": "Верхняя неделя",
        "Аудитория": {
          "Корпус": "У",
          "Номер аудитории": "167"
        },
        "Группа": "5216",
        "Предмет": {
          "Наименование предмета": "Цифровые трансформации в судостроении",
          "Тип занятия": "Лекция",
          "Дополнительная информация": ""
        },
        "Преподаватель": {
          "Фамилия": "Липис",
          "Имя": "Алексей",
          "Отчество": "Викторович"
        }
      },
      {
        "Время": "19:00-20:30",
        "Неделя": "Нижняя неделя",
        "Аудитория": {
          "Корпус": "У",
          "Номер аудитории": "439"
        },
        "Группа": "5216",
        "Предмет": {
          "Наименование предмета": "Цифровые трансформации в судостроении",
          "Тип занятия": "Практическое занятие",
          "Дополнительная информация": ""
        },
        "Преподаватель": {
          "Фамилия": "Липис",
          "Имя": "Алексей",
          "Отчество": "Викторович"
        }
      },
      {
        "Время": "20:40-22:10",
        "Неделя": "Верхняя неделя",
        "Аудитория": {
          "Корпус": "У",
          "Номер аудитории": "440"
        },
        "Группа": "5216",
        "Предмет": {
          "Наименование предмета": "Логистика",
          "Тип занятия": "Лекция",
          "Дополнительная информация": ""
        },
        "Преподаватель": {
          "Фамилия": "Талеров",
          "Имя": "Павел",
          "Отчество": "Иванович"
        }
      },
      {
        "Время": "20:40-22:10",
        "Неделя": "Нижняя неделя",
        "Аудитория": {
          "Корпус": "У",
          "Номер аудитории": "439"
        },
        "Группа": "5216",
        "Предмет": {
          "Наименование предмета": "Цифровые трансформации в судостроении",
          "Тип занятия": "Практическое занятие",
          "Дополнительная информация": ""
        },
        "Преподаватель": {
          "Фамилия": "Липис",
          "Имя": "Алексей",
          "Отчество": "Викторович"
        }
      }
    ]
  },
  {
    "День недели": "Четверг",
    "Расписание": [
      {
        "Время": "19:00-20:30",
        "Неделя": "Верхняя неделя",
        "Аудитория": {
          "Корпус": "Б",
          "Номер аудитории": "218"
        },
        "Группа": "5216",
        "Предмет": {
          "Наименование предмета": "Строительная механика и прочность корабля",
          "Тип занятия": "Лекция",
          "Дополнительная информация": ""
        },
        "Преподаватель": {
          "Фамилия": "Миронов",
          "Имя": "Михаил",
          "Отчество": "Юрьевич"
        }
      },
      {
        "Время": "19:00-20:30",
        "Неделя": "Нижняя неделя",
        "Аудитория": {
          "Корпус": "Б",
          "Номер аудитории": "218"
        },
        "Группа": "5216",
        "Предмет": {
          "Наименование предмета": "Строительная механика и прочность корабля",
          "Тип занятия": "Практическое занятие",
          "Дополнительная информация": ""
        },
        "Преподаватель": {
          "Фамилия": "Мудрик",
          "Имя": "Роман",
          "Отчество": "Сергеевич"
        }
      },
      {
        "Время": "20:40-22:10",
        "Неделя": "Верхняя неделя",
        "Аудитория": {
          "Корпус": "Б",
          "Номер аудитории": "508"
        },
        "Группа": "5216",
        "Предмет": {
          "Наименование предмета": "Проектирование ледоколов и судов ледового плавания",
          "Тип занятия": "Лекция",
          "Дополнительная информация": ""
        },
        "Преподаватель": {
          "Фамилия": "Ионов",
          "Имя": "Борис",
          "Отчество": "Петрович"
        }
      },
      {
        "Время": "20:40-22:10",
        "Неделя": "Нижняя неделя",
        "Аудитория": {
          "Корпус": "Б",
          "Номер аудитории": "508"
        },
        "Группа": "5216",
        "Предмет": {
          "Наименование предмета": "Проектирование ледоколов и судов ледового плавания",
          "Тип занятия": "Практическое занятие",
          "Дополнительная информация": ""
        },
        "Преподаватель": {
          "Фамилия": "Ионов",
          "Имя": "Борис",
          "Отчество": "Петрович"
        }
      }
    ]
  },
  {
    "День недели": "Пятница",
    "Расписание": [
      {
        "Время": "19:00-20:30",
        "Неделя": "Обе недели",
        "Аудитория": {
          "Корпус": "У",
          "Номер аудитории": "174"
        },
        "Группа": "5216",
        "Предмет": {
          "Наименование предмета": "Бережливое производство в судостроении",
          "Тип занятия": "Практическое занятие",
          "Дополнительная информация": "с 1 по 22 ноября"
        },
        "Преподаватель": {
          "Фамилия": "Загребельный",
          "Имя": "Кирилл",
          "Отчество": "Александрович"
        }
      },
      {
        "Время": "19:00-20:30",
        "Неделя": "Обе недели",
        "Аудитория": {
          "Корпус": "Б",
          "Номер аудитории": "401"
        },
        "Группа": "5216",
        "Предмет": {
          "Наименование предмета": "Бережливое производство в судостроении",
          "Тип занятия": "Лекция",
          "Дополнительная информация": "с 4 по 25 октября"
        },
        "Преподаватель": {
          "Фамилия": "Загребельный",
          "Имя": "Кирилл",
          "Отчество": "Александрович"
        }
      },
      {
        "Время": "20:40-22:10",
        "Неделя": "Обе недели",
        "Аудитория": {
          "Корпус": "У",
          "Номер аудитории": "174"
        },
        "Группа": "5216",
        "Предмет": {
          "Наименование предмета": "Бережливое производство в судостроении",
          "Тип занятия": "Практическое занятие",
          "Дополнительная информация": "с 1 по 22 ноября"
        },
        "Преподаватель": {
          "Фамилия": "Загребельный",
          "Имя": "Кирилл",
          "Отчество": "Александрович"
        }
      },
      {
        "Время": "20:40-22:10",
        "Неделя": "Обе недели",
        "Аудитория": {
          "Корпус": "Б",
          "Номер аудитории": "401"
        },
        "Группа": "5216",
        "Предмет": {
          "Наименование предмета": "Бережливое производство в судостроении",
          "Тип занятия": "Лекция",
          "Дополнительная информация": "с 4 по 25 октября"
        },
        "Преподаватель": {
          "Фамилия": "Загребельный",
          "Имя": "Кирилл",
          "Отчество": "Александрович"
        }
      }
    ]
  }
]